github_exposed_email_crawler/__init__.py
github_exposed_email_crawler/script.py
exposed_github_user_emails_scanner-1.0.7.dist-info/LICENSE
exposed_github_user_emails_scanner-1.0.7.dist-info/METADATA
exposed_github_user_emails_scanner-1.0.7.dist-info/WHEEL
exposed_github_user_emails_scanner-1.0.7.dist-info/entry_points.txt
exposed_github_user_emails_scanner-1.0.7.dist-info/top_level.txt
exposed_github_user_emails_scanner-1.0.7.dist-info/RECORD
