Metadata-Version: 2.1
Name: exposed_github_user_emails_scanner
Version: 1.0.7
Summary: A cli script to find exposed email addresses of one GitHub user in his or her public repositories.
Home-page: https://github.com/wahlflo/showExposedGitHubEmails
Author: Florian Wahl
Author-email: florian.wahl.developer@gmail.com
Classifier: Programming Language :: Python :: 3
Classifier: License :: OSI Approved :: MIT License
Classifier: Operating System :: OS Independent
License-File: LICENSE
Requires-Dist: cli-formatter >=1.1.0
Requires-Dist: requests
